{"moduleName":null,"summaries":[{"symbol":{"__symbol":0,"members":[]},"metadata":{"__symbol":1,"members":[]}},{"symbol":{"__symbol":2,"members":[]},"metadata":{"__symbol":3,"members":[]}},{"symbol":{"__symbol":4,"members":[]},"metadata":{"__symbol":5,"members":[]}},{"symbol":{"__symbol":6,"members":[]},"metadata":{"__symbol":7,"members":[]}}],"symbols":[{"__symbol":0,"name":"AckOffline","filePath":"./index"},{"__symbol":1,"name":"AckOffline","filePath":"./AckOffline"},{"__symbol":2,"name":"AckCache","filePath":"./index"},{"__symbol":3,"name":"AckCache","filePath":"./AckCache"},{"__symbol":4,"name":"AckQue","filePath":"./index"},{"__symbol":5,"name":"AckQue","filePath":"./AckQue"},{"__symbol":6,"name":"AckApi","filePath":"./index"},{"__symbol":7,"name":"AckApi","filePath":"./AckApi"}]}